pypde/__init__.py
pypde/cfuncs.py
pypde/solvers.py
pypde/utils.py
pypde/build/libpypde.1.0.0.dylib
pypde/build/libpypde.dylib
pypde/tests/__init__.py
pypde/tests/exact.py
pypde/tests/euler/__init__.py
pypde/tests/euler/system.py
pypde/tests/gpr/__init__.py
pypde/tests/gpr/params.py
pypde/tests/gpr/system.py
pypde/tests/gpr/misc/__init__.py
pypde/tests/gpr/misc/eos.py
pypde/tests/gpr/misc/functions.py
pypde/tests/gpr/misc/mg.py
pypde/tests/gpr/misc/sources.py
pypde/tests/gpr/misc/state.py
pypde/tests/gpr/misc/utils.py
pypde/tests/navier_stokes/__init__.py
pypde/tests/navier_stokes/system.py
pypde/tests/reactive_euler/__init__.py
pypde/tests/reactive_euler/system.py
PyPDE-1.0.0.dist-info/LICENSE
PyPDE-1.0.0.dist-info/METADATA
PyPDE-1.0.0.dist-info/WHEEL
PyPDE-1.0.0.dist-info/top_level.txt
PyPDE-1.0.0.dist-info/RECORD
