Metadata-Version: 2.1
Name: PyPDE
Version: 1.0.0
Summary: Solve any hyperbolic/parabolic system of PDEs
Home-page: https://github.com/haranjackson/pypde
Author: Haran Jackson
Author-email: jackson.haran@gmail.com
License: UNKNOWN
Keywords: ADER,WENO,Discontinuous Galerkin,Finite Volume,PDEs,Partial Differential Equations,Hyperbolic,Parabolic
Platform: UNKNOWN
Classifier: License :: OSI Approved :: GNU Affero General Public License v3 or later (AGPLv3+)
Classifier: Programming Language :: Python :: 3.6
Classifier: Programming Language :: Python :: 3.7
Classifier: Programming Language :: Python :: 3.8
Requires-Python: >=3.6
Requires-Dist: numba (>=0.46)
Requires-Dist: numpy (>=1.14)
